pyclimenu/__init__.py
pyclimenu/cli_menu.py
pyclimenu/menu.py
pyclimenu/menu_item.py
cli_menu_decorator-0.0.1.dist-info/LICENSE
cli_menu_decorator-0.0.1.dist-info/METADATA
cli_menu_decorator-0.0.1.dist-info/WHEEL
cli_menu_decorator-0.0.1.dist-info/top_level.txt
cli_menu_decorator-0.0.1.dist-info/RECORD
